BotApiTelegram/__init__.py
BotApiTelegram/bot.py
BotApiTelegram/conversation.py
BotApiTelegram/database.py
BotApiTelegram/exceptions.py
BotApiTelegram/filters.py
BotApiTelegram/methods.py
BotApiTelegram/tools.py
BotApiTelegram/types.py
BotApiTelegram-0.0.8.dist-info/METADATA
BotApiTelegram-0.0.8.dist-info/WHEEL
BotApiTelegram-0.0.8.dist-info/top_level.txt
BotApiTelegram-0.0.8.dist-info/RECORD
