Metadata-Version: 2.1
Name: BotApiTelegram
Version: 0.0.8
Summary: A python library for Telegram Bot Api.
Home-page: https://github.com/SastaDev/BotApiTelegram/archive/refs/tags/v0.0.8.tar.gz
Download-URL: https://github.com/SastaDev/BotApiTelegram
Author: Sasta Dev
Author-email: sastadev2007@gmail.com
License: GNU General Public License v3.0
Keywords: BotApiTelegram
Classifier: Development Status :: 3 - Alpha
Classifier: Intended Audience :: Developers
Classifier: Topic :: Software Development :: Build Tools
Requires-Dist: requests
